Workbook

Sheet Instructions
A1: EXCEL CUSTOMER TRANSACTION ANALYSIS – SOLUTION GUIDE
A3: 1. Raw Data | B3: 100 sample customer transactions are included. Replace them with your actual dataset if your teacher supplied one.
A4: 2. Date & Time | B4: TODAY(), NOW(), DATEDIF(), TEXT() and EDATE() are demonstrated.
A5: 3. FILTER | B5: Analysis!A12 returns multiple Electronics records using FILTER.
A6: 4. Conditional Formatting | B6: Analysis!G12:G21 highlights customer revenue using a color scale.
A7: 5. Timestamp | B7: What-If & Regression!B18 uses NOW(); press F9 to recalculate.
A8: 6. What-If | B8: Scenario table is provided. Actual Goal Seek: Data → What-If Analysis → Goal Seek.
A9: 7. Linear Regression | B9: SLOPE, INTERCEPT, RSQ and CORREL are included; ToolPak path: Data → Data Analysis → Regression.
A10: 8. GroupBy Concept | B10: Customer revenue and transaction counts are grouped with SUMIF/COUNTIF.
A11: 9. Dashboard | B11: Dashboard contains KPI indicators plus Bar, Line and Pie charts.
A12: 10. Slicers & Timeline | B12: Create PivotTables from Raw Data, then add Slicers and a Timeline.
A13: 11. Compare Lists | B13: Analysis!C31:C40 extracts matching names from two lists.
A14: 12. Abbreviations | B14: Analysis!F31:F40 creates 3-letter abbreviations using LEFT/TEXT-related functions.
A15: 13. Final Story | B15: Report Total Revenue, Total Transactions, Most Purchased Product, Most Frequent Customer and Regional/Monthly trends.

Sheet Raw Data
A1: Transaction ID | B1: Date | C1: Time | D1: Customer | E1: Region | F1: Product | G1: Category | H1: Quantity | I1: Unit Price | J1: Revenue | K1: Payment Method | L1: Customer Type | M1: Salesperson
A2: T0001 | B2: 46080 | C2: 0.45833333 | D2: Ananya | E2: North | F2: Laptop | G2: Electronics | H2: 3 | I2: 52194 | J2: 156582 | K2: Net Banking | L2: New | M2: Amit
A3: T0002 | B3: 46070 | C3: 0.375 | D3: Riya | E3: South | F3: Headphones | G3: Accessories | H3: 2 | I3: 3504 | J3: 7008 | K3: Net Banking | L3: New | M3: Sneha
A4: T0003 | B4: 46165 | C4: 0.58333333 | D4: Kabir | E4: South | F4: Laptop | G4: Electronics | H4: 2 | I4: 57180 | J4: 114360 | K4: Card | L4: Returning | M4: Amit
A5: T0004 | B5: 46070 | C5: 0.58333333 | D5: Pooja | E5: East | F5: Printer | G5: Office | H5: 1 | I5: 9232 | J5: 9232 | K5: UPI | L5: Returning | M5: Raj
A6: T0005 | B6: 46086 | C6: 0.79166667 | D6: Pooja | E6: East | F6: Printer | G6: Office | H6: 1 | I6: 9599 | J6: 9599 | K6: Card | L6: New | M6: Amit
A7: T0006 | B7: 46139 | C7: 0.41666667 | D7: Rahul | E7: East | F7: Keyboard | G7: Accessories | H7: 1 | I7: 1928 | J7: 1928 | K7: Net Banking | L7: Returning | M7: Neha
A8: T0007 | B8: 46212 | C8: 0.83333333 | D8: Rohan | E8: South | F8: Monitor | G8: Electronics | H8: 2 | I8: 12408 | J8: 24816 | K8: Card | L8: New | M8: Sneha
A9: T0008 | B9: 46217 | C9: 0.58333333 | D9: Diya | E9: South | F9: Keyboard | G9: Accessories | H9: 5 | I9: 1699 | J9: 8495 | K9: UPI | L9: Returning | M9: Sneha
A10: T0009 | B10: 46160 | C10: 0.75 | D10: Aditya | E10: South | F10: Smartphone | G10: Electronics | H10: 2 | I10: 30314 | J10: 60628 | K10: Net Banking | L10: Returning | M10: Sneha
A11: T0010 | B11: 46096 | C11: 0.70833333 | D11: Riya | E11: East | F11: Keyboard | G11: Accessories | H11: 2 | I11: 1709 | J11: 3418 | K11: Net Banking | L11: Returning | M11: Kunal
A12: T0011 | B12: 46135 | C12: 0.375 | D12: Ananya | E12: South | F12: Tablet | G12: Electronics | H12: 5 | I12: 17977 | J12: 89885 | K12: Card | L12: Returning | M12: Raj
A13: T0012 | B13: 46055 | C13: 0.66666667 | D13: Yash | E13: East | F13: Printer | G13: Office | H13: 4 | I13: 9682 | J13: 38728 | K13: UPI | L13: New | M13: Raj
... A101: T0100 | B101: 46170 | C101: 0.58333333 | D101: Dev | E101: East | F101: Tablet | G101: Electronics | H101: 1 | I101: 17790 | J101: 17790 | K101: Net Banking | L101: Returning | M101: Sneha

Sheet Analysis
A1: CUSTOMER TRANSACTION ANALYSIS
A3: Date & Time Functions | D3: Key Metrics
A4: Today | B4: =TODAY() | D4: Total Revenue | E4: =SUM('Raw Data'!J2:J101)
A5: Current Time | B5: =NOW() | D5: Total Transactions | E5: =COUNTA('Raw Data'!A2:A101)
A6: Days from First Transaction | B6: =DATEDIF(MIN('Raw Data'!B2:B101),TODAY(),"d") | D6: Total Quantity | E6: =SUM('Raw Data'!H2:H101)
A7: Transaction Month | B7: =TEXT('Raw Data'!B2,"mmm-yyyy") | D7: Average Order Value | E7: =AVERAGE('Raw Data'!J2:J101)
D8: Unique Customers | E8: =SUMPRODUCT(1/COUNTIF('Raw Data'!D2:D101,'Raw Data'!D2:D101))
A10: FILTER Example – Electronics Transactions | F10: High-Value Customers
A11: Transaction ID | B11: Customer | C11: Product | D11: Revenue | F11: Customer | G11: Revenue | H11: Transactions
A12: =FILTER(CHOOSE({1,2,3,4},'Raw Data'!A2:A101,'Raw Data'!D2:D101,'Raw Data'!F2:F101,'Raw Data'!J2:J101),'Raw Data'!G2:G101="Electronics","No matches") | F12: Aarav | G12: =SUMIF('Raw Data'!D:D,F12,'Raw Data'!J:J) | H12: =COUNTIF('Raw Data'!D:D,F12)
F13: Diya | G13: =SUMIF('Raw Data'!D:D,F13,'Raw Data'!J:J) | H13: =COUNTIF('Raw Data'!D:D,F13)
F14: Rohan | G14: =SUMIF('Raw Data'!D:D,F14,'Raw Data'!J:J) | H14: =COUNTIF('Raw Data'!D:D,F14)
F15: Ananya | G15: =SUMIF('Raw Data'!D:D,F15,'Raw Data'!J:J) | H15: =COUNTIF('Raw Data'!D:D,F15)
F16: Vivaan | G16: =SUMIF('Raw Data'!D:D,F16,'Raw Data'!J:J) | H16: =COUNTIF('Raw Data'!D:D,F16)
F17: Ishita | G17: =SUMIF('Raw Data'!D:D,F17,'Raw Data'!J:J) | H17: =COUNTIF('Raw Data'!D:D,F17)
F18: Arjun | G18: =SUMIF('Raw Data'!D:D,F18,'Raw Data'!J:J) | H18: =COUNTIF('Raw Data'!D:D,F18)
F19: Meera | G19: =SUMIF('Raw Data'!D:D,F19,'Raw Data'!J:J) | H19: =COUNTIF('Raw Data'!D:D,F19)
F20: Kabir | G20: =SUMIF('Raw Data'!D:D,F20,'Raw Data'!J:J) | H20: =COUNTIF('Raw Data'!D:D,F20)
F21: Saanvi | G21: =SUMIF('Raw Data'!D:D,F21,'Raw Data'!J:J) | H21: =COUNTIF('Raw Data'!D:D,F21)
A25: Most Purchased Product | B25: =INDEX('Raw Data'!F2:F101,MODE(MATCH('Raw Data'!F2:F101,'Raw Data'!F2:F101,0)))
A26: Most Frequent Customer | B26: =INDEX('Raw Data'!D2:D101,MODE(MATCH('Raw Data'!D2:D101,'Raw Data'!D2:D101,0)))
A29: Compare Two Lists | E29: Abbreviations using TEXT functions
A30: List A | B30: List B | C30: Matching Name | E30: Customer | F30: Abbreviation
A31: Aarav | B31: Ishita | C31: =IF(COUNTIF(B:B,A31)>0,A31,"") | E31: Aarav | F31: =UPPER(LEFT(E31,3))
A32: Diya | B32: Arjun | C32: =IF(COUNTIF(B:B,A32)>0,A32,"") | E32: Diya | F32: =UPPER(LEFT(E32,3))
A33: Rohan | B33: Meera | C33: =IF(COUNTIF(B:B,A33)>0,A33,"") | E33: Rohan | F33: =UPPER(LEFT(E33,3))
A34: Ananya | B34: Kabir | C34: =IF(COUNTIF(B:B,A34)>0,A34,"") | E34: Ananya | F34: =UPPER(LEFT(E34,3))
A35: Vivaan | B35: Saanvi | C35: =IF(COUNTIF(B:B,A35)>0,A35,"") | E35: Vivaan | F35: =UPPER(LEFT(E35,3))
A36: Ishita | B36: Aditya | C36: =IF(COUNTIF(B:B,A36)>0,A36,"") | E36: Ishita | F36: =UPPER(LEFT(E36,3))
A37: Arjun | B37: Priya | C37: =IF(COUNTIF(B:B,A37)>0,A37,"") | E37: Arjun | F37: =UPPER(LEFT(E37,3))
A38: Meera | B38: Rahul | C38: =IF(COUNTIF(B:B,A38)>0,A38,"") | E38: Meera | F38: =UPPER(LEFT(E38,3))
A39: Kabir | B39: Nisha | C39: =IF(COUNTIF(B:B,A39)>0,A39,"") | E39: Kabir | F39: =UPPER(LEFT(E39,3))
A40: Saanvi | B40: Karan | C40: =IF(COUNTIF(B:B,A40)>0,A40,"") | E40: Saanvi | F40: =UPPER(LEFT(E40,3))

Sheet Monthly Analysis
A1: MONTHLY SALES ANALYSIS
A3: Month | B3: Revenue | C3: Transactions | D3: Quantity | E3: Average Order Value
A4: 46023 | B4: =SUMIFS('Raw Data'!J:J,'Raw Data'!B:B,">="&A4,'Raw Data'!B:B,"<"&EDATE(A4,1)) | C4: =COUNTIFS('Raw Data'!B:B,">="&A4,'Raw Data'!B:B,"<"&EDATE(A4,1)) | D4: =SUMIFS('Raw Data'!H:H,'Raw Data'!B:B,">="&A4,'Raw Data'!B:B,"<"&EDATE(A4,1)) | E4: =IFERROR(B4/C4,0)
A5: 46054 | B5: =SUMIFS('Raw Data'!J:J,'Raw Data'!B:B,">="&A5,'Raw Data'!B:B,"<"&EDATE(A5,1)) | C5: =COUNTIFS('Raw Data'!B:B,">="&A5,'Raw Data'!B:B,"<"&EDATE(A5,1)) | D5: =SUMIFS('Raw Data'!H:H,'Raw Data'!B:B,">="&A5,'Raw Data'!B:B,"<"&EDATE(A5,1)) | E5: =IFERROR(B5/C5,0)
A6: 46082 | B6: =SUMIFS('Raw Data'!J:J,'Raw Data'!B:B,">="&A6,'Raw Data'!B:B,"<"&EDATE(A6,1)) | C6: =COUNTIFS('Raw Data'!B:B,">="&A6,'Raw Data'!B:B,"<"&EDATE(A6,1)) | D6: =SUMIFS('Raw Data'!H:H,'Raw Data'!B:B,">="&A6,'Raw Data'!B:B,"<"&EDATE(A6,1)) | E6: =IFERROR(B6/C6,0)
A7: 46113 | B7: =SUMIFS('Raw Data'!J:J,'Raw Data'!B:B,">="&A7,'Raw Data'!B:B,"<"&EDATE(A7,1)) | C7: =COUNTIFS('Raw Data'!B:B,">="&A7,'Raw Data'!B:B,"<"&EDATE(A7,1)) | D7: =SUMIFS('Raw Data'!H:H,'Raw Data'!B:B,">="&A7,'Raw Data'!B:B,"<"&EDATE(A7,1)) | E7: =IFERROR(B7/C7,0)
A8: 46143 | B8: =SUMIFS('Raw Data'!J:J,'Raw Data'!B:B,">="&A8,'Raw Data'!B:B,"<"&EDATE(A8,1)) | C8: =COUNTIFS('Raw Data'!B:B,">="&A8,'Raw Data'!B:B,"<"&EDATE(A8,1)) | D8: =SUMIFS('Raw Data'!H:H,'Raw Data'!B:B,">="&A8,'Raw Data'!B:B,"<"&EDATE(A8,1)) | E8: =IFERROR(B8/C8,0)
A9: 46174 | B9: =SUMIFS('Raw Data'!J:J,'Raw Data'!B:B,">="&A9,'Raw Data'!B:B,"<"&EDATE(A9,1)) | C9: =COUNTIFS('Raw Data'!B:B,">="&A9,'Raw Data'!B:B,"<"&EDATE(A9,1)) | D9: =SUMIFS('Raw Data'!H:H,'Raw Data'!B:B,">="&A9,'Raw Data'!B:B,"<"&EDATE(A9,1)) | E9: =IFERROR(B9/C9,0)
A10: 46204 | B10: =SUMIFS('Raw Data'!J:J,'Raw Data'!B:B,">="&A10,'Raw Data'!B:B,"<"&EDATE(A10,1)) | C10: =COUNTIFS('Raw Data'!B:B,">="&A10,'Raw Data'!B:B,"<"&EDATE(A10,1)) | D10: =SUMIFS('Raw Data'!H:H,'Raw Data'!B:B,">="&A10,'Raw Data'!B:B,"<"&EDATE(A10,1)) | E10: =IFERROR(B10/C10,0)
A11: 46235 | B11: =SUMIFS('Raw Data'!J:J,'Raw Data'!B:B,">="&A11,'Raw Data'!B:B,"<"&EDATE(A11,1)) | C11: =COUNTIFS('Raw Data'!B:B,">="&A11,'Raw Data'!B:B,"<"&EDATE(A11,1)) | D11: =SUMIFS('Raw Data'!H:H,'Raw Data'!B:B,">="&A11,'Raw Data'!B:B,"<"&EDATE(A11,1)) | E11: =IFERROR(B11/C11,0)
A12: 46266 | B12: =SUMIFS('Raw Data'!J:J,'Raw Data'!B:B,">="&A12,'Raw Data'!B:B,"<"&EDATE(A12,1)) | C12: =COUNTIFS('Raw Data'!B:B,">="&A12,'Raw Data'!B:B,"<"&EDATE(A12,1)) | D12: =SUMIFS('Raw Data'!H:H,'Raw Data'!B:B,">="&A12,'Raw Data'!B:B,"<"&EDATE(A12,1)) | E12: =IFERROR(B12/C12,0)

Sheet Regional Analysis
A1: REGIONAL SALES ANALYSIS
A3: Region | B3: Revenue | C3: Transactions | D3: Quantity | E3: Revenue Share
A4: North | B4: =SUMIF('Raw Data'!E:E,A4,'Raw Data'!J:J) | C4: =COUNTIF('Raw Data'!E:E,A4) | D4: =SUMIF('Raw Data'!E:E,A4,'Raw Data'!H:H) | E4: =B4/SUM($B$4:$B$7)
A5: South | B5: =SUMIF('Raw Data'!E:E,A5,'Raw Data'!J:J) | C5: =COUNTIF('Raw Data'!E:E,A5) | D5: =SUMIF('Raw Data'!E:E,A5,'Raw Data'!H:H) | E5: =B5/SUM($B$4:$B$7)
A6: East | B6: =SUMIF('Raw Data'!E:E,A6,'Raw Data'!J:J) | C6: =COUNTIF('Raw Data'!E:E,A6) | D6: =SUMIF('Raw Data'!E:E,A6,'Raw Data'!H:H) | E6: =B6/SUM($B$4:$B$7)
A7: West | B7: =SUMIF('Raw Data'!E:E,A7,'Raw Data'!J:J) | C7: =COUNTIF('Raw Data'!E:E,A7) | D7: =SUMIF('Raw Data'!E:E,A7,'Raw Data'!H:H) | E7: =B7/SUM($B$4:$B$7)

Sheet What-If & Regression
A1: WHAT-IF ANALYSIS & LINEAR REGRESSION
A3: Goal Seek Example | E3: Linear Regression
A4: Current Revenue | B4: =SUM('Raw Data'!J2:J101)
A5: Target Revenue | B5: 10000000
A6: Required Growth % | B6: =B5/B4-1
A7: Goal Seek: Data → What-If Analysis → Goal Seek; set B4 to B5 by changing the chosen growth/input cell. | E7: Slope | F7: =SLOPE('Raw Data'!J2:J101,'Raw Data'!H2:H101)
E8: Intercept | F8: =INTERCEPT('Raw Data'!J2:J101,'Raw Data'!H2:H101)
E9: R² | F9: =RSQ('Raw Data'!J2:J101,'Raw Data'!H2:H101)
A10: Scenario Manager-style table | E10: Correlation | F10: =CORREL('Raw Data'!J2:J101,'Raw Data'!H2:H101)
A11: Scenario | B11: Revenue Growth | C11: Projected Revenue
A12: Base | B12: 0 | C12: =$B$4*(1+B12)
A13: Growth | B13: 0.1 | C13: =$B$4*(1+B13)
A14: High Growth | B14: 0.2 | C14: =$B$4*(1+B14)
A15: Decline | B15: -0.1 | C15: =$B$4*(1+B15)
A18: Timestamp | B18: =NOW()
A19: Refresh with F9 when workbook recalculates.

Sheet Category Analysis
A1: Category | B1: Revenue
A2: Electronics | B2: =SUMIF('Raw Data'!G:G,A2,'Raw Data'!J:J)
A3: Accessories | B3: =SUMIF('Raw Data'!G:G,A3,'Raw Data'!J:J)
A4: Office | B4: =SUMIF('Raw Data'!G:G,A4,'Raw Data'!J:J)
A5: Furniture | B5: =SUMIF('Raw Data'!G:G,A5,'Raw Data'!J:J)

Sheet Dashboard
A1: CUSTOMER SALES DASHBOARD
A3: Total Revenue | C3: Transactions | E3: Quantity Sold | G3: Avg Order Value
A4: =Analysis!E4 | C4: =Analysis!E5 | E4: =Analysis!E6 | G4: =Analysis!E7
E22: Products
E23: Product | F23: Revenue
E24: Laptop | F24: =SUMIF('Raw Data'!F:F,E24,'Raw Data'!J:J)
E25: Smartphone | F25: =SUMIF('Raw Data'!F:F,E25,'Raw Data'!J:J)
E26: Tablet | F26: =SUMIF('Raw Data'!F:F,E26,'Raw Data'!J:J)
E27: Headphones | F27: =SUMIF('Raw Data'!F:F,E27,'Raw Data'!J:J)
E28: Keyboard | F28: =SUMIF('Raw Data'!F:F,E28,'Raw Data'!J:J)
E29: Monitor | F29: =SUMIF('Raw Data'!F:F,E29,'Raw Data'!J:J)
E30: Printer | F30: =SUMIF('Raw Data'!F:F,E30,'Raw Data'!J:J)
E31: Chair | F31: =SUMIF('Raw Data'!F:F,E31,'Raw Data'!J:J)
A39: Slicers & Timeline
A40: In Excel: Insert → PivotTable from Raw Data, then Insert → Slicer (Region/Category/Customer Type) and Insert → Timeline (Date).
